sopel_modules.checkiday-0.2.0-py3.7-nspkg.pth
sopel_modules/checkiday/__init__.py
sopel_modules/checkiday/checkiday.py
tests/__init__.py
tests/test_checkiday.py
sopel_modules.checkiday-0.2.0.dist-info/COPYING
sopel_modules.checkiday-0.2.0.dist-info/METADATA
sopel_modules.checkiday-0.2.0.dist-info/WHEEL
sopel_modules.checkiday-0.2.0.dist-info/namespace_packages.txt
sopel_modules.checkiday-0.2.0.dist-info/top_level.txt
sopel_modules.checkiday-0.2.0.dist-info/RECORD
