Metadata-Version: 1.0
Name: sopel_modules.checkiday
Version: 0.2.0
Summary: A plugin that returns today's holidays from checkiday.com
Home-page: https://github.com/shanedabes/sopel-checkiday
Author: Shane Donohoe
Author-email: shane@isda.best
License: Eiffel Forum License, version 2
Platform: UNKNOWN
